deepserve_cli-0.4.0.data/scripts/deepserve
src/CLI.py
src/__init__.py
src/commands/AuthCommand.py
src/commands/DeployCommand.py
src/commands/ProjectsCommand.py
src/commands/__init__.py
src/helpers/__init__.py
src/helpers/colorprint.py
src/helpers/error_boundary.py
src/helpers/localstorage.py
src/interfaces/APIInterface.py
src/interfaces/GraphQLInterface.py
src/interfaces/S3Interface.py
src/interfaces/__init__.py
src/steps/AuthAndConnectStep.py
src/steps/CreateVersionStep.py
src/steps/InitiateDeployStep.py
src/steps/MonitorDeployStep.py
src/steps/UploadModelStep.py
src/steps/UploadNotebookStep.py
src/steps/__init__.py
deepserve_cli-0.4.0.dist-info/LICENSE
deepserve_cli-0.4.0.dist-info/METADATA
deepserve_cli-0.4.0.dist-info/WHEEL
deepserve_cli-0.4.0.dist-info/top_level.txt
deepserve_cli-0.4.0.dist-info/RECORD
