Metadata-Version: 2.1
Name: deepserve-cli
Version: 0.4.0
Summary: A CLI package for deepserve.ai
Home-page: https://github.com/deepserve/deepserve-cli
Author: Jeff Wells
Author-email: jeff@deepserve.ai
License: UNKNOWN
Platform: UNKNOWN
Classifier: Programming Language :: Python :: 3
Classifier: License :: OSI Approved :: MIT License
Classifier: Operating System :: OS Independent
Requires-Dist: gql (==2.0.0)
Requires-Dist: halo
Requires-Dist: termcolor
Requires-Dist: requests
Requires-Dist: tabulate
Requires-Dist: fire
